sotooncli/__init__.py
sotooncli/cache_utils.py
sotooncli/config_utils.py
sotooncli/main.py
sotooncli/param_types.py
sotooncli/repo.py
sotooncli/requests.py
sotooncli/settings.py
sotooncli/state.py
sotooncli/utils.py
sotooncli/version.py
sotooncli/core/__init__.py
sotooncli/core/command.py
sotooncli/core/context.py
sotooncli/core/decorators.py
sotooncli/core/help_formatter.py
sotooncli/core/param.py
sotooncli/core/response.py
sotooncli/globals/__init__.py
sotooncli/globals/config.py
sotooncli/globals/options.py
sotooncli/globals/output_format.py
sotooncli/sotoon/__init__.py
sotooncli/sotoon/cache.py
sotooncli/sotoon/config.py
sotooncli/sotoon/options.py
sotooncli-0.0.6.dist-info/DESCRIPTION.rst
sotooncli-0.0.6.dist-info/METADATA
sotooncli-0.0.6.dist-info/RECORD
sotooncli-0.0.6.dist-info/WHEEL
sotooncli-0.0.6.dist-info/entry_points.txt
sotooncli-0.0.6.dist-info/metadata.json
sotooncli-0.0.6.dist-info/top_level.txt
